artix_engine/__init__.py
artix_engine/main.py
artix_engine/types.py
artix_engine-0.0.4.dist-info/METADATA
artix_engine-0.0.4.dist-info/WHEEL
artix_engine-0.0.4.dist-info/top_level.txt
artix_engine-0.0.4.dist-info/RECORD
